bin/__init__.py
bin/conpot
bin/kamstrup_prober.py
conpot/__init__.py
conpot/data.tar
conpot/helpers.py
conpot/testing.cfg
conpot/core/__init__.py
conpot/core/attack_session.py
conpot/core/databus.py
conpot/core/filesystem.py
conpot/core/fs_utils.py
conpot/core/internal_interface.py
conpot/core/protocol_wrapper.py
conpot/core/session_manager.py
conpot/core/virtual_fs.py
conpot/core/loggers/__init__.py
conpot/core/loggers/helpers.py
conpot/core/loggers/hpfriends.py
conpot/core/loggers/json_log.py
conpot/core/loggers/log_worker.py
conpot/core/loggers/mysql_log.py
conpot/core/loggers/sqlite_log.py
conpot/core/loggers/stix_transform.py
conpot/core/loggers/syslog.py
conpot/core/loggers/taxii_log.py
conpot/emulators/__init__.py
conpot/emulators/proxy.py
conpot/emulators/proxy.xsd
conpot/emulators/misc/__init__.py
conpot/emulators/misc/uptime.py
conpot/emulators/sensors/__init__.py
conpot/protocols/__init__.py
conpot/protocols/IEC104/DeviceDataController.py
conpot/protocols/IEC104/IEC104.py
conpot/protocols/IEC104/IEC104.xsd
conpot/protocols/IEC104/IEC104_server.py
conpot/protocols/IEC104/__init__.py
conpot/protocols/IEC104/errors.py
conpot/protocols/IEC104/frames.py
conpot/protocols/IEC104/i_frames_check.py
conpot/protocols/IEC104/register.py
conpot/protocols/bacnet/__init__.py
conpot/protocols/bacnet/bacnet.xsd
conpot/protocols/bacnet/bacnet_app.py
conpot/protocols/bacnet/bacnet_server.py
conpot/protocols/enip/__init__.py
conpot/protocols/enip/enip.xsd
conpot/protocols/enip/enip_server.py
conpot/protocols/ftp/__init__.py
conpot/protocols/ftp/ftp.xsd
conpot/protocols/ftp/ftp_base_handler.py
conpot/protocols/ftp/ftp_handler.py
conpot/protocols/ftp/ftp_server.py
conpot/protocols/ftp/ftp_utils.py
conpot/protocols/guardian_ast/__init__.py
conpot/protocols/guardian_ast/guardian_ast.xsd
conpot/protocols/guardian_ast/guardian_ast_server.py
conpot/protocols/http/__init__.py
conpot/protocols/http/command_responder.py
conpot-0.6.0.dist-info/METADATA
conpot-0.6.0.dist-info/RECORD
conpot-0.6.0.dist-info/WHEEL
conpot-0.6.0.dist-info/dependency_links.txt
conpot-0.6.0.dist-info/top_level.txt
