Metadata-Version: 2.1
Name: conpot
Version: 0.6.0
Summary: Conpot is an ICS honeypot with the goal to collect intelligence about the motives
Home-page: http://conpot.org
Author: MushMush Foundation
Author-email: hello@mushmush.org
License: GPL 2
Keywords: ICS SCADA honeypot
Platform: UNKNOWN
Classifier: Development Status :: 4 - Beta
Classifier: Environment :: Console
Classifier: Intended Audience :: Developers
Classifier: License :: OSI Approved :: GNU General Public License v2 (GPLv2)
Classifier: Operating System :: POSIX :: Linux
Classifier: Programming Language :: Python :: 3 :: Only
Classifier: Programming Language :: Python :: 3.5
Classifier: Programming Language :: Python
Classifier: Topic :: Security
Requires-Python: >=3.5
Requires-Dist: gevent (>=1.0)
Requires-Dist: pysnmp
Requires-Dist: pysmi
Requires-Dist: lxml
Requires-Dist: bottle
Requires-Dist: jinja2
Requires-Dist: beautifulsoup4
Requires-Dist: requests
Requires-Dist: sphinx
Requires-Dist: libtaxii (>=1.1.0)
Requires-Dist: xlrd
Requires-Dist: crc16
Requires-Dist: natsort
Requires-Dist: scapy
Requires-Dist: enum34
Requires-Dist: hpfeeds3
Requires-Dist: modbus-tk
Requires-Dist: stix-validator
Requires-Dist: stix
Requires-Dist: pycrypto
Requires-Dist: cybox
Requires-Dist: bacpypes (==0.17.0)
Requires-Dist: pyghmi
Requires-Dist: mixbox
Requires-Dist: modbus-tk
Requires-Dist: cpppo
Requires-Dist: pytest
Requires-Dist: fs
Requires-Dist: python-slugify
Requires-Dist: tftpy
Requires-Dist: freezegun
Requires-Dist: pytest
Requires-Dist: tox
